Metadata-Version: 2.1
Name: topsis-rythm-102218039
Version: 1.0.0
Summary: Python library for dealing with Multiple Criteria Decision Making(MCDM) problems by using Technique for Order of Preference by Similarity to Ideal Solution(TOPSIS).
Home-page: https://github.com/Rythm17/topsis
Author: RythmGagneja
Author-email: 
License: MIT
Classifier: License :: OSI Approved :: MIT License
Classifier: Programming Language :: Python :: 3.6
Classifier: Programming Language :: Python :: 3.7
Classifier: Programming Language :: Python :: 3.8
License-File: LICENSE
